poraque/__init__.py
poraque/_version.py
poraque-0.0.3.dist-info/METADATA
poraque-0.0.3.dist-info/WHEEL
poraque-0.0.3.dist-info/licenses/LICENSE
poraque-0.0.3.dist-info/RECORD
