Metadata-Version: 2.4
Name: poraque
Version: 0.0.3
Summary: Electronic structure with graph neural networks
Project-URL: Homepage, https://github.com/seixasgroup/poraque
Author-email: Leandro Seixas <leandro.fisica@gmail.com>
License: MIT License
License-File: LICENSE
Classifier: License :: OSI Approved :: MIT License
Classifier: Operating System :: OS Independent
Classifier: Programming Language :: Python :: 3
Classifier: Topic :: Scientific/Engineering :: Chemistry
Classifier: Topic :: Scientific/Engineering :: Physics
Requires-Python: >=3.10
Requires-Dist: ase
Requires-Dist: matplotlib
Requires-Dist: networkx
Requires-Dist: numpy
Requires-Dist: pandas
Requires-Dist: scipy
Requires-Dist: torch
